faas_metric/__init__.py
faas_metric/cli.py
faas_metric/compute.py
faas_metric-1.0.2.dist-info/METADATA
faas_metric-1.0.2.dist-info/WHEEL
faas_metric-1.0.2.dist-info/entry_points.txt
faas_metric-1.0.2.dist-info/top_level.txt
faas_metric-1.0.2.dist-info/RECORD
