Metadata-Version: 2.4
Name: faas-metric
Version: 1.0.2
Summary: Fairness Adjusted ASR Score Metric
Author: Your Name
License: MIT
Classifier: Programming Language :: Python :: 3
Requires-Dist: pandas
